{"name": "北京联合大学", "province_name": "北京", "rank": 181, "school_id": 575}
{"name": "南京邮电大学", "province_name": "江苏", "rank": 182, "school_id": 160}
{"name": "重庆文理学院", "province_name": "重庆", "rank": 183, "school_id": 1038}
{"name": "西安建筑科技大学", "province_name": "陕西", "rank": 184, "school_id": 351}
{"name": "南通大学", "province_name": "江苏", "rank": 185, "school_id": 787}
{"name": "中国药科大学", "province_name": "江苏", "rank": 186, "school_id": 117}
{"name": "河南师范大学", "province_name": "河南", "rank": 187, "school_id": 833}
{"name": "南京工业大学", "province_name": "江苏", "rank": 188, "school_id": 171}
{"name": "华东政法大学", "province_name": "上海", "rank": 189, "school_id": 323}
{"name": "西安工业大学", "province_name": "陕西", "rank": 190, "school_id": 361}
{"name": "三峡大学", "province_name": "湖北", "rank": 191, "school_id": 431}
{"name": "山东交通学院", "province_name": "山东", "rank": 192, "school_id": 534}
{"name": "中国矿业大学", "province_name": "江苏", "rank": 193, "school_id": 110}
{"name": "四川农业大学", "province_name": "四川", "rank": 194, "school_id": 100}
{"name": "中南民族大学", "province_name": "湖北", "rank": 195, "school_id": 423}
{"name": "华北科技学院", "province_name": "河北", "rank": 196, "school_id": 604}
{"name": "西安石油大学", "province_name": "陕西", "rank": 197, "school_id": 354}
{"name": "江西师范大学", "province_name": "江西", "rank": 198, "school_id": 174}
{"name": "山东工商学院", "province_name": "山东", "rank": 199, "school_id": 526}
{"name": "中国计量大学", "province_name": "浙江", "rank": 200, "school_id": 247}
